_fastoad/__init__.py
fast_oad-1.8.4.dist-info/METADATA
fast_oad-1.8.4.dist-info/WHEEL
fast_oad-1.8.4.dist-info/RECORD
