Metadata-Version: 2.1
Name: FAST-OAD
Version: 1.8.4
Summary: FAST-OAD is a framework for performing rapid Overall Aircraft Design
Home-page: https://github.com/fast-aircraft-design/FAST-OAD
License: GPL-3.0-only
Keywords: aircraft,design,multi-disciplinary
Author: Christophe DAVID
Author-email: christophe.david@onera.fr
Requires-Python: >=3.8,<4.0
Classifier: Development Status :: 5 - Production/Stable
Classifier: Environment :: Console
Classifier: Intended Audience :: Education
Classifier: Intended Audience :: Science/Research
Classifier: License :: OSI Approved :: GNU General Public License v3 (GPLv3)
Classifier: Natural Language :: English
Classifier: Operating System :: MacOS
Classifier: Operating System :: Microsoft :: Windows
Classifier: Operating System :: POSIX :: Linux
Classifier: Programming Language :: Python :: 3
Classifier: Programming Language :: Python :: 3.8
Classifier: Programming Language :: Python :: 3.9
Classifier: Programming Language :: Python :: 3.10
Classifier: Programming Language :: Python :: 3.11
Classifier: Programming Language :: Python :: 3.12
Classifier: Topic :: Scientific/Engineering :: Physics
Requires-Dist: fast-oad-core (>=1.8.4,<2.0.0)
Requires-Dist: fast-oad-cs25 (>=0.1.4)
